voicebox/__init__.py
voicebox/corpus.py
voicebox/ngram.py
voicebox-0.0.2.dist-info/DESCRIPTION.rst
voicebox-0.0.2.dist-info/METADATA
voicebox-0.0.2.dist-info/RECORD
voicebox-0.0.2.dist-info/WHEEL
voicebox-0.0.2.dist-info/metadata.json
voicebox-0.0.2.dist-info/top_level.txt
