Metadata-Version: 2.0
Name: voicebox
Version: 0.0.2
Summary: Predictive text writing tool
Home-page: UNKNOWN
Author: Jamie Brew
Author-email: UNKNOWN
License: UNKNOWN
Platform: UNKNOWN
Requires-Dist: nose (==1.3.7)
